M13_pypi_daspro/__init__.py
M13_pypi_daspro/guess_number.py
M13_pypi_daspro/weight_conversion.py
M13_pypi_daspro-0.1.0.dist-info/METADATA
M13_pypi_daspro-0.1.0.dist-info/WHEEL
M13_pypi_daspro-0.1.0.dist-info/top_level.txt
M13_pypi_daspro-0.1.0.dist-info/RECORD
