Metadata-Version: 2.1
Name: M13-pypi-daspro
Version: 0.1.0
Summary: A library to convert weights and guess numbers
Author: Azani Fattur Fadhika
Author-email: affadhika287@gmail.com
Classifier: Programming Language :: Python :: 3
Classifier: License :: OSI Approved :: MIT License
Classifier: Operating System :: OS Independent
Requires-Python: >=3.6
